{
  "arch": "x86_64",
  "build": "he870216_1",
  "build_number": 1,
  "channel": "https://repo.anaconda.com/pkgs/main/linux-64",
  "constrains": [],
  "depends": [
    "pip",
    "ld_impl_linux-64",
    "tzdata",
    "libgcc-ng >=11.2.0",
    "libstdcxx-ng >=11.2.0",
    "zlib >=1.2.13,<1.3.0a0",
    "libffi >=3.4,<4.0a0",
    "libffi >=3.4,<3.5",
    "ncurses >=6.4,<7.0a0",
    "xz >=5.4.6,<6.0a0",
    "openssl >=3.0.15,<4.0a0",
    "sqlite >=3.45.3,<4.0a0",
    "tk >=8.6.14,<8.7.0a0",
    "readline >=8.1.2,<9.0a0"
  ],
  "fn": "python-3.9.20-he870216_1.conda",
  "license": "PSF-2.0",
  "license_family": "PSF",
  "md5": "7e6ef6ff36ff2dc0aed5f566d2287bb9",
  "name": "python",
  "platform": "linux",
  "sha256": "2d4bbed6fe15353e1363b0ca3b9c74ef9945f030313e5379e13796824c08abd6",
  "size": 26341886,
  "subdir": "linux-64",
  "timestamp": 1727941108000,
  "url": "https://repo.anaconda.com/pkgs/main/linux-64/python-3.9.20-he870216_1.conda",
  "version": "3.9.20"
}